steam_pysigma/MainPySIGMA.py
steam_pysigma/__init__.py
steam_pysigma/comsol/BuildComsolModel.py
steam_pysigma/comsol/BuildGlobalVariables.py
steam_pysigma/comsol/__init__.py
steam_pysigma/data/DataPySIGMA.py
steam_pysigma/data/DataRoxieParser.py
steam_pysigma/data/DataSettings.py
steam_pysigma/data/__init__.py
steam_pysigma/domain_generator/GeometryMultipole.py
steam_pysigma/domain_generator/__init__.py
steam_pysigma/plotters/PlotterPysigma.py
steam_pysigma/plotters/PlotterRoxie.py
steam_pysigma/plotters/__init__.py
steam_pysigma/postprocessing/__init__.py
steam_pysigma/postprocessing/postprocessing.py
steam_pysigma/sigma/__init__.py
steam_pysigma/sigma/pysigma.py
steam_pysigma/sigma/steam-sigma-2025.2.0.jar
steam_pysigma/utils/CFUN_mapping.csv
steam_pysigma/utils/Utils.py
steam_pysigma/utils/__init__.py
steam_pysigma-2025.2.0.dist-info/LICENSE.txt
steam_pysigma-2025.2.0.dist-info/METADATA
steam_pysigma-2025.2.0.dist-info/WHEEL
steam_pysigma-2025.2.0.dist-info/top_level.txt
steam_pysigma-2025.2.0.dist-info/RECORD
