Metadata-Version: 2.1
Name: steam-pysigma
Version: 2025.2.0
Summary: This is python wrapper of STEAM SIGMA code
Home-page: https://gitlab.cern.ch/steam/steam_pysigma
Author: STEAM Team
Author-email: steam-team@cern.ch
Keywords: SIGMA,CERN,STEAM
Classifier: Programming Language :: Python :: 3.11
Requires-Python: >=3.11.8
License-File: LICENSE.txt
Requires-Dist: py4j ==0.10.9.7
Requires-Dist: matplotlib ==3.8.3
Requires-Dist: numpy ==1.26.4
Requires-Dist: pandas ==2.2.1
Requires-Dist: pydantic ==2.6.4
Requires-Dist: ruamel.yaml ==0.18.6
Provides-Extra: all
Requires-Dist: py4j ==0.10.9.7 ; extra == 'all'
Requires-Dist: matplotlib ==3.8.3 ; extra == 'all'
Requires-Dist: numpy ==1.26.4 ; extra == 'all'
Requires-Dist: pandas ==2.2.1 ; extra == 'all'
Requires-Dist: pydantic ==2.6.4 ; extra == 'all'
Requires-Dist: ruamel.yaml ==0.18.6 ; extra == 'all'
Requires-Dist: Markdown ==3.5.2 ; extra == 'all'
Requires-Dist: markdown-include ==0.8.1 ; extra == 'all'
Requires-Dist: MarkupSafe ==2.1.5 ; extra == 'all'
Requires-Dist: mkdocs ==1.5.3 ; extra == 'all'
Requires-Dist: mkdocs-autorefs ==1.0.1 ; extra == 'all'
Requires-Dist: mkdocs-git-revision-date-localized-plugin ==1.2.4 ; extra == 'all'
Requires-Dist: mkdocs-include-markdown-plugin ==6.0.4 ; extra == 'all'
Requires-Dist: mkdocs-material ==9.5.13 ; extra == 'all'
Requires-Dist: mkdocs-material-extensions ==1.3.1 ; extra == 'all'
Requires-Dist: mkdocstrings ==0.24.1 ; extra == 'all'
Requires-Dist: mkdocstrings-python ==1.9.0 ; extra == 'all'
Requires-Dist: Pygments ==2.17.2 ; extra == 'all'
Requires-Dist: pymdown-extensions ==10.7.1 ; extra == 'all'
Requires-Dist: coverage ==7.4.3 ; extra == 'all'
Requires-Dist: coverage-badge ==1.1.0 ; extra == 'all'
Requires-Dist: griffe ==0.42.0 ; extra == 'all'
Requires-Dist: pytest ==8.1.1 ; extra == 'all'
Requires-Dist: pytest-cov ==4.1.0 ; extra == 'all'
Requires-Dist: setuptools ==69.2.0 ; extra == 'all'
Provides-Extra: build
Requires-Dist: setuptools ==69.2.0 ; extra == 'build'
Provides-Extra: docs
Requires-Dist: Markdown ==3.5.2 ; extra == 'docs'
Requires-Dist: markdown-include ==0.8.1 ; extra == 'docs'
Requires-Dist: MarkupSafe ==2.1.5 ; extra == 'docs'
Requires-Dist: mkdocs ==1.5.3 ; extra == 'docs'
Requires-Dist: mkdocs-autorefs ==1.0.1 ; extra == 'docs'
Requires-Dist: mkdocs-git-revision-date-localized-plugin ==1.2.4 ; extra == 'docs'
Requires-Dist: mkdocs-include-markdown-plugin ==6.0.4 ; extra == 'docs'
Requires-Dist: mkdocs-material ==9.5.13 ; extra == 'docs'
Requires-Dist: mkdocs-material-extensions ==1.3.1 ; extra == 'docs'
Requires-Dist: mkdocstrings ==0.24.1 ; extra == 'docs'
Requires-Dist: mkdocstrings-python ==1.9.0 ; extra == 'docs'
Requires-Dist: Pygments ==2.17.2 ; extra == 'docs'
Requires-Dist: pymdown-extensions ==10.7.1 ; extra == 'docs'
Provides-Extra: tests
Requires-Dist: coverage ==7.4.3 ; extra == 'tests'
Requires-Dist: coverage-badge ==1.1.0 ; extra == 'tests'
Requires-Dist: griffe ==0.42.0 ; extra == 'tests'
Requires-Dist: pytest ==8.1.1 ; extra == 'tests'
Requires-Dist: pytest-cov ==4.1.0 ; extra == 'tests'
